lintel/__init__.py
lintel/__main__.py
lintel/_check_source.py
lintel/_config.py
lintel/_docstring.py
lintel/_docstring_error.py
lintel/_file_discovery.py
lintel/_get_checks.py
lintel/_get_error_codes.py
lintel/_utils.py
lintel/_version.py
lintel/_wordlists.py
lintel/cli.py
lintel/checks/__init__.py
lintel/checks/blank_lines.py
lintel/checks/capitalized.py
lintel/checks/empty_docstring.py
lintel/checks/indentation.py
lintel/checks/missing_docstring.py
lintel/checks/mood.py
lintel/checks/newline_after_last_paragraph.py
lintel/checks/one_liner.py
lintel/checks/overload.py
lintel/checks/punctuation.py
lintel/checks/quotation.py
lintel/checks/sections.py
lintel/checks/signature.py
lintel/checks/starts_with_this.py
lintel/checks/summary_start.py
lintel/checks/surrounding_spaces.py
lintel/data/__init__.py
lintel/data/imperatives.txt
lintel/data/imperatives_blacklist.txt
lintel-0.1.0.dist-info/LICENSE-MIT
lintel-0.1.0.dist-info/METADATA
lintel-0.1.0.dist-info/WHEEL
lintel-0.1.0.dist-info/entry_points.txt
lintel-0.1.0.dist-info/top_level.txt
lintel-0.1.0.dist-info/RECORD
