Metadata-Version: 2.1
Name: lintel
Version: 0.1.0
Summary: Python docstring style checker
Home-page: https://github.com/Mr-Pepe/lintel/
Author: Felipe Peter
Author-email: mr-peipei@web.de
License: MIT
Keywords: lintel,pydocstyle,PEP 257,pep257,PEP 8,pep8,docstrings
Classifier: Intended Audience :: Developers
Classifier: Environment :: Console
Classifier: Programming Language :: Python :: 3
Classifier: Programming Language :: Python :: 3.8
Classifier: Programming Language :: Python :: 3.9
Classifier: Programming Language :: Python :: 3.10
Classifier: Programming Language :: Python :: 3.11
Classifier: Programming Language :: Python :: 3 :: Only
Classifier: Operating System :: OS Independent
Classifier: License :: OSI Approved :: MIT License
Requires-Python: >=3.8
License-File: LICENSE-MIT
Requires-Dist: typer[all] (>=0.9.0)
Requires-Dist: rich
Requires-Dist: pydantic
Requires-Dist: snowballstemmer (>=1.2.1)
Requires-Dist: astroid (>=2.0)
Requires-Dist: tomli (>=1.2.3) ; python_version < "3.11"
Provides-Extra: build
Requires-Dist: build[virtualenv] ; extra == 'build'
Provides-Extra: dev
Requires-Dist: tox ; extra == 'dev'
Requires-Dist: toml (==0.10.2) ; extra == 'dev'
Requires-Dist: isort ; extra == 'dev'
Requires-Dist: black ; extra == 'dev'
Requires-Dist: mypy ; extra == 'dev'
Requires-Dist: types-docutils ; extra == 'dev'
Requires-Dist: pytest ; extra == 'dev'
Requires-Dist: pytest-cov ; extra == 'dev'
Requires-Dist: coverage[toml] ; extra == 'dev'
Requires-Dist: pytest-randomly ; extra == 'dev'
Requires-Dist: pytest-xdist ; extra == 'dev'
Requires-Dist: sphinx ; extra == 'dev'
Requires-Dist: sphinx-rtd-theme ; extra == 'dev'
Requires-Dist: build[virtualenv] ; extra == 'dev'
Provides-Extra: doc
Requires-Dist: sphinx ; extra == 'doc'
Requires-Dist: sphinx-rtd-theme ; extra == 'doc'
Provides-Extra: lint
Requires-Dist: isort ; extra == 'lint'
Requires-Dist: black ; extra == 'lint'
Requires-Dist: mypy ; extra == 'lint'
Requires-Dist: types-docutils ; extra == 'lint'
Provides-Extra: test
Requires-Dist: pytest ; extra == 'test'
Requires-Dist: pytest-cov ; extra == 'test'
Requires-Dist: coverage[toml] ; extra == 'test'
Requires-Dist: pytest-randomly ; extra == 'test'
Requires-Dist: pytest-xdist ; extra == 'test'
Provides-Extra: toml
Requires-Dist: toml (==0.10.2) ; extra == 'toml'
